README.rst
setup.py
sslchecker/__init__.py
sslchecker/cli.py
sslchecker/lib.py
sslchecker/sslcert.py
sslchecker.egg-info/PKG-INFO
sslchecker.egg-info/SOURCES.txt
sslchecker.egg-info/dependency_links.txt
sslchecker.egg-info/entry_points.txt
sslchecker.egg-info/pbr.json
sslchecker.egg-info/requires.txt
sslchecker.egg-info/top_level.txt