Metadata-Version: 1.1
Name: sslchecker
Version: 0.1.5
Summary: Check SSL certificates of a site on your command line
Home-page: https://github.com/raccoonyy/sslchecker
Author: Seungho Kim
Author-email: raccoonyy@gmail.com
License: UNKNOWN
Platform: UNKNOWN
Classifier: Development Status :: 4 - Beta
Classifier: Environment :: Console
Classifier: Operating System :: POSIX
Classifier: Programming Language :: Python :: 2.7
Classifier: Topic :: Utilities
